pycgmes/__init__.py
pycgmes/resources/ACDCConverter.py
pycgmes/resources/ACDCConverterDCTerminal.py
pycgmes/resources/ACDCTerminal.py
pycgmes/resources/ACLineSegment.py
pycgmes/resources/Accumulator.py
pycgmes/resources/AccumulatorLimit.py
pycgmes/resources/AccumulatorLimitSet.py
pycgmes/resources/AccumulatorReset.py
pycgmes/resources/AccumulatorValue.py
pycgmes/resources/ActivePower.py
pycgmes/resources/ActivePowerLimit.py
pycgmes/resources/ActivePowerPerCurrentFlow.py
pycgmes/resources/ActivePowerPerFrequency.py
pycgmes/resources/Analog.py
pycgmes/resources/AnalogControl.py
pycgmes/resources/AnalogLimit.py
pycgmes/resources/AnalogLimitSet.py
pycgmes/resources/AnalogValue.py
pycgmes/resources/AngleDegrees.py
pycgmes/resources/AngleRadians.py
pycgmes/resources/ApparentPower.py
pycgmes/resources/ApparentPowerLimit.py
pycgmes/resources/Area.py
pycgmes/resources/AsynchronousMachine.py
pycgmes/resources/AsynchronousMachineDynamics.py
pycgmes/resources/AsynchronousMachineEquivalentCircuit.py
pycgmes/resources/AsynchronousMachineKind.py
pycgmes/resources/AsynchronousMachineTimeConstantReactance.py
pycgmes/resources/AsynchronousMachineUserDefined.py
pycgmes/resources/AuxiliaryEquipment.py
pycgmes/resources/BaseVoltage.py
pycgmes/resources/BasicIntervalSchedule.py
pycgmes/resources/BatteryStateKind.py
pycgmes/resources/BatteryUnit.py
pycgmes/resources/Bay.py
pycgmes/resources/Boolean.py
pycgmes/resources/BoundaryPoint.py
pycgmes/resources/Breaker.py
pycgmes/resources/BusNameMarker.py
pycgmes/resources/BusbarSection.py
pycgmes/resources/CAESPlant.py
pycgmes/resources/CSCDynamics.py
pycgmes/resources/CSCUserDefined.py
pycgmes/resources/Capacitance.py
pycgmes/resources/Clamp.py
pycgmes/resources/CogenerationPlant.py
pycgmes/resources/CombinedCyclePlant.py
pycgmes/resources/Command.py
pycgmes/resources/Conductance.py
pycgmes/resources/ConductingEquipment.py
pycgmes/resources/Conductor.py
pycgmes/resources/ConformLoad.py
pycgmes/resources/ConformLoadGroup.py
pycgmes-2.0.6.dist-info/LICENSE
pycgmes-2.0.6.dist-info/LICENSES/Apache-2.0.txt
pycgmes-2.0.6.dist-info/LICENSES/CC-BY-4.0.txt
pycgmes-2.0.6.dist-info/METADATA
pycgmes-2.0.6.dist-info/WHEEL
pycgmes-2.0.6.dist-info/RECORD
