Metadata-Version: 2.3
Name: pycgmes
Version: 2.0.6
Summary: Python dataclasses for CGMES 3.0.0
License: Apache 2.0
Author: pycgmes
Author-email: pycgmes@alliander.com
Requires-Python: >=3.11,<4.0
Classifier: Development Status :: 5 - Production/Stable
Classifier: Framework :: Pydantic
Classifier: License :: OSI Approved :: Apache Software License
Classifier: License :: Other/Proprietary License
Classifier: Operating System :: OS Independent
Classifier: Programming Language :: Python :: 3
Classifier: Programming Language :: Python :: 3.11
Classifier: Programming Language :: Python :: 3.12
Classifier: Programming Language :: Python :: 3.13
Classifier: Topic :: Software Development :: Libraries :: Python Modules
Classifier: Typing :: Typed
Requires-Dist: chevron (>=0.14.0)
Requires-Dist: poetry (>=1.5.0)
Requires-Dist: pydantic (>=2)
Project-URL: Repository, https://github.com/alliander-opensource/pycgmes
